pastep/__init__.py
pastep/pastep.py
pastep-1.0.9.dist-info/License.txt
pastep-1.0.9.dist-info/METADATA
pastep-1.0.9.dist-info/WHEEL
pastep-1.0.9.dist-info/top_level.txt
pastep-1.0.9.dist-info/RECORD
