Metadata-Version: 2.1
Name: pastep
Version: 1.0.9
Summary: Pastep API module
Home-page: https://pastep.com
Author: Pooria Ahmadi
Author-email: pooriababak444@gmail.com
License: MIT
Platform: UNKNOWN
Classifier: Programming Language :: Python :: 3
Classifier: License :: OSI Approved :: MIT License
Classifier: Operating System :: OS Independent
Requires-Dist: requests
